grug_test/__init__.py
grug_test/main.py
grug_test/settings.json
grug_test/test.py
grug_test/__dependencies__/__init__.py
grug_test/__dependencies__/__sources__/blissful_basics/.gitignore
grug_test/__dependencies__/__sources__/blissful_basics/.gitrepo
grug_test/__dependencies__/__sources__/blissful_basics/README.md
grug_test/__dependencies__/__sources__/blissful_basics/poetry.lock
grug_test/__dependencies__/__sources__/blissful_basics/pyproject.toml
grug_test/__dependencies__/__sources__/blissful_basics/main/license.txt
grug_test/__dependencies__/__sources__/blissful_basics/main/setup.py
grug_test/__dependencies__/__sources__/blissful_basics/main/blissful_basics/__init__.py
grug_test/__dependencies__/__sources__/blissful_basics/main/blissful_basics/settings.json
grug_test/__dependencies__/__sources__/blissful_basics/main/blissful_basics/update_dependencies
grug_test/__dependencies__/__sources__/blissful_basics/main/blissful_basics/__dependencies__/__init__.py
grug_test/__dependencies__/__sources__/blissful_basics/main/blissful_basics/__dependencies__/__sources__/file_system_py/.gitignore
grug_test/__dependencies__/__sources__/blissful_basics/main/blissful_basics/__dependencies__/__sources__/file_system_py/.gitrepo
grug_test/__dependencies__/__sources__/blissful_basics/main/blissful_basics/__dependencies__/__sources__/file_system_py/README.md
grug_test/__dependencies__/__sources__/blissful_basics/main/blissful_basics/__dependencies__/__sources__/file_system_py/poetry.lock
grug_test/__dependencies__/__sources__/blissful_basics/main/blissful_basics/__dependencies__/__sources__/file_system_py/pyproject.toml
grug_test/__dependencies__/__sources__/blissful_basics/main/blissful_basics/__dependencies__/__sources__/file_system_py/logs/main.py.log
grug_test/__dependencies__/__sources__/blissful_basics/main/blissful_basics/__dependencies__/__sources__/file_system_py/main/license.txt
grug_test-0.2.0.dist-info/METADATA
grug_test-0.2.0.dist-info/WHEEL
grug_test-0.2.0.dist-info/top_level.txt
grug_test-0.2.0.dist-info/RECORD
