Metadata-Version: 2.1
Name: grug_test
Version: 0.2.0
Summary: Tests for lazy (smart) devs
Home-page: https://github.com/jeff-hykin/grug_test_py
Author: Jeff Hykin
Author-email: jeff.hykin@gmail.com
License: MIT
Platform: UNKNOWN
Requires-Python: >=3.6
